setup.py
mx_asyns/__init__.py
mx_asyns/decorator.py
mx_asyns/heartbeat.py
mx_asyns/tasks.py
mx_asyns/tools.py
mx_asyns/web.py
mx_helpers.egg-info/PKG-INFO
mx_helpers.egg-info/SOURCES.txt
mx_helpers.egg-info/dependency_links.txt
mx_helpers.egg-info/top_level.txt
mx_utils/__init__.py
mx_utils/logUtil.py
mx_utils/notice.py
mx_utils/randomUtil.py
mx_utils/redisClient.py
mx_utils/singleton.py
mx_utils/web.py