Metadata-Version: 2.1
Name: mx-helpers
Version: 0.0.2
Summary: 封装自用帮助库
Home-page: UNKNOWN
Author: MiXian
Author-email: xlin0721@163.com
License: UNKNOWN
Platform: UNKNOWN
Classifier: Programming Language :: Python :: 3
Classifier: License :: OSI Approved :: MIT License
Classifier: Operating System :: OS Independent
Requires-Python: >=3.6
